zbrac/__init__.py
zbrac/__main__.py
zbrac/functions.py
zbrac/interface.py
zbrac/mainwindow.py
zbrac/resources_rc.py
zbrac/start.py
zbrac-1.0.10.dist-info/LICENSE
zbrac-1.0.10.dist-info/METADATA
zbrac-1.0.10.dist-info/WHEEL
zbrac-1.0.10.dist-info/entry_points.txt
zbrac-1.0.10.dist-info/top_level.txt
zbrac-1.0.10.dist-info/RECORD
