Metadata-Version: 2.1
Name: zbrac
Version: 1.0.10
Summary: A multilanguage tool for zTree
Home-page: https://github.com/seyhunsaral/zbrac
Author: Ali Seyhun Saral, Anna Marie Schroeter
Author-email: seyhunsaral@gmail.com, schroeter@coll.mpg.de
License: GNU GPL-3
Requires-Python: >3.6.0
License-File: LICENSE
Requires-Dist: openpyxl (>=2.5.8)
Requires-Dist: PyQt5 (>=5.11.3)
Requires-Dist: PyQt5-sip (>=4.19.13)
Requires-Dist: PyQt5.sip (>=4.19.13)
Requires-Dist: urllib3 (>=1.24.1)
Requires-Dist: XlsxWriter (>=1.1.1)
